bio_parser/__init__.py
bio_parser/cli.py
bio_parser/utils.py
bio_parser/parse/__init__.py
bio_parser/parse/document.py
bio_parser/parse/exceptions.py
bio_parser/parse/validate.py
tests/__init__.py
tests/test_utils.py
tests/parse/__init__.py
tests/parse/test_document.py
tests/parse/test_validate.py
bio_parser-0.3.0.dist-info/LICENSE
bio_parser-0.3.0.dist-info/METADATA
bio_parser-0.3.0.dist-info/WHEEL
bio_parser-0.3.0.dist-info/entry_points.txt
bio_parser-0.3.0.dist-info/top_level.txt
bio_parser-0.3.0.dist-info/RECORD
