Metadata-Version: 2.1
Name: bio-parser
Version: 0.3.0
Author-email: Oliver Tüselmann <oliver.tueselmann@tu-dortmund.de>, David Villanova Aparisi <davilap@inf.upv.es>, Yoann Schneider <yschneider@teklia.com>, Solène Tarride <starride@teklia.com>
Maintainer-email: Yoann Schneider <yschneider@teklia.com>, Solène Tarride <starride@teklia.com>
License: MIT License
Project-URL: Homepage, https://gitlab.teklia.com/ner/metrics/bio-parser
Project-URL: Documentation, https://ner.pages.teklia.com/metrics/bio-parser
Project-URL: Repository, https://gitlab.teklia.com/ner/metrics/bio-parser
Project-URL: Bug Tracker, https://gitlab.teklia.com/ner/metrics/bio-parser/issues
Keywords: NER,python
Classifier: Development Status :: 5 - Production/Stable
Classifier: License :: OSI Approved :: MIT License
Classifier: Programming Language :: Python :: 3 :: Only
Classifier: Programming Language :: Python :: 3.10
Classifier: Topic :: Scientific/Engineering :: Artificial Intelligence
Classifier: Topic :: Text Processing :: Linguistic
Requires-Python: >=3.10
License-File: LICENSE
Requires-Dist: rich ==13.7.0
Provides-Extra: docs
Requires-Dist: black ==23.11.0 ; extra == 'docs'
Requires-Dist: mkdocs-autorefs ==0.5.0 ; extra == 'docs'
Requires-Dist: mkdocs-literate-nav ==0.6.1 ; extra == 'docs'
Requires-Dist: mkdocs-material ==9.4.5 ; extra == 'docs'
Requires-Dist: mkdocstrings ==0.24.0 ; extra == 'docs'
Requires-Dist: mkdocstrings-python ==1.7.4 ; extra == 'docs'
